zephyr_kconfig/__about__.py
zephyr_kconfig/__init__.py
zephyr_kconfig/__main__.py
zephyr_kconfig/_doc_loaders.py
zephyr_kconfig/_locations.py
zephyr_kconfig/_models.py
zephyr_kconfig/_types.py
zephyr_kconfig-0.2.1.dist-info/METADATA
zephyr_kconfig-0.2.1.dist-info/WHEEL
zephyr_kconfig-0.2.1.dist-info/entry_points.txt
zephyr_kconfig-0.2.1.dist-info/licenses/LICENSE
zephyr_kconfig-0.2.1.dist-info/RECORD
